ray_peewee/__init__.py
ray_peewee/all.py
ray_peewee-0.2.0.dist-info/DESCRIPTION.rst
ray_peewee-0.2.0.dist-info/METADATA
ray_peewee-0.2.0.dist-info/RECORD
ray_peewee-0.2.0.dist-info/WHEEL
ray_peewee-0.2.0.dist-info/metadata.json
ray_peewee-0.2.0.dist-info/top_level.txt
