Metadata-Version: 2.0
Name: ray-peewee
Version: 0.2.0
Summary: UNKNOWN
Home-page: http://github.com/felipevolpone/ray
Author: Felipe Volpone
Author-email: felipevolpone@gmail.com
License: MIT
Keywords: ray_peewee peewee framework ray api rest
Platform: UNKNOWN
Classifier: Development Status :: 3 - Alpha
Classifier: Topic :: Utilities
Requires-Dist: peewee
